gpui/__init__.py
gpui-0.0.1.dist-info/METADATA
gpui-0.0.1.dist-info/WHEEL
gpui-0.0.1.dist-info/licenses/LICENSE
gpui-0.0.1.dist-info/RECORD
