Metadata-Version: 2.4
Name: gpui
Version: 0.0.1
Summary: Zed's GPUI for Python
Author-email: Lex Berezhny <lex@damoti.com>
License:                                  Apache License
License-File: LICENSE
Requires-Python: >=3.12
